CHANGES.md
LICENSE
MANIFEST.in
README.md
requirements.txt
setup.py
test/test_gwnsql.py
test/test_gwnxml.py
test/test_main.py
test/test_models.py
test/test_omwsql.py
test/test_wnsql.py
yawlib/__init__.py
yawlib/__main__.py
yawlib/__version__.py
yawlib/common.py
yawlib/config.py
yawlib/helpers.py
yawlib/models.py
yawlib/omwsql.py
yawlib/wntk.py
yawlib/wordnetsql.py
yawlib.egg-info/PKG-INFO
yawlib.egg-info/SOURCES.txt
yawlib.egg-info/dependency_links.txt
yawlib.egg-info/requires.txt
yawlib.egg-info/top_level.txt
yawlib/data/config_template.json
yawlib/glosswordnet/__init__.py
yawlib/glosswordnet/gwnmodels.py
yawlib/glosswordnet/gwnsqlite.py
yawlib/glosswordnet/gwnxml.py
yawlib/glosswordnet/script/gwn_setup.sql
yawlib/yawol/__init__.py
yawlib/yawol/app.py
yawlib/yawol/django/__init__.py
yawlib/yawol/django/admin.py
yawlib/yawol/django/apps.py
yawlib/yawol/django/models.py
yawlib/yawol/django/tests.py
yawlib/yawol/django/urls.py
yawlib/yawol/django/views.py
yawlib/yawol/django/migrations/__init__.py