Metadata-Version: 2.1
Name: yawlib
Version: 0.1
Summary: Python library for accessing major wordnet releases using relational databases for high performance batch processing
Home-page: https://github.com/letuananh/yawlib
Author: Le Tuan Anh
Author-email: tuananh.ke@gmail.com
License: MIT License
Project-URL: Bug Tracker, https://github.com/letuananh/yawlib/issues
Project-URL: Source Code, https://github.com/letuananh/yawlib/
Keywords: wordnet,glosstag,omw,sqlite
Platform: any
Classifier: Programming Language :: Python
Classifier: Development Status :: 5 - Production/Stable
Classifier: Natural Language :: English
Classifier: Environment :: Plugins
Classifier: Intended Audience :: Developers
Classifier: Intended Audience :: Science/Research
Classifier: License :: OSI Approved :: MIT License
Classifier: Operating System :: OS Independent
Classifier: Topic :: Text Processing
Classifier: Topic :: Text Processing :: Linguistic
Classifier: Topic :: Software Development :: Libraries :: Python Modules
